steadytext/__init__.py
steadytext/__main__.py
steadytext/cache_manager.py
steadytext/config.py
steadytext/disk_backed_frecency_cache.py
steadytext/download.py
steadytext/exceptions.py
steadytext/frecency_cache.py
steadytext/sqlite_cache_backend.py
steadytext/utils.py
steadytext/cache/__init__.py
steadytext/cache/base.py
steadytext/cache/d1_backend.py
steadytext/cache/factory.py
steadytext/cache/memory_backend.py
steadytext/cache/sqlite_backend.py
steadytext/cli/__init__.py
steadytext/cli/__main__.py
steadytext/cli/main.py
steadytext/cli/commands/__init__.py
steadytext/cli/commands/cache.py
steadytext/cli/commands/completion.py
steadytext/cli/commands/daemon.py
steadytext/cli/commands/embed.py
steadytext/cli/commands/generate.py
steadytext/cli/commands/index.py
steadytext/cli/commands/models.py
steadytext/cli/commands/rerank.py
steadytext/cli/commands/set_default.py
steadytext/cli/commands/vector.py
steadytext/cli/zsh-plugin/README.md
steadytext/cli/zsh-plugin/_steadytext_async
steadytext/cli/zsh-plugin/example-config.zsh
steadytext/cli/zsh-plugin/install.sh
steadytext/cli/zsh-plugin/steadytext-autosuggestions.zsh
steadytext/cli/zsh-plugin/steadytext-context.plugin.zsh
steadytext/cli/zsh-plugin/examples/demo.md
steadytext/core/CLAUDE.md
steadytext/core/__init__.py
steadytext/core/embedder.py
steadytext/core/generator.py
steadytext/core/grammar.py
steadytext/core/reranker.py
steadytext/core/structured.py
steadytext/daemon/__init__.py
steadytext/daemon/client.py
steadytext/daemon/protocol.py
steadytext/daemon/server.py
steadytext/models/CLAUDE.md
steadytext/models/__init__.py
steadytext/models/cache.py
steadytext/models/loader.py
steadytext/providers/__init__.py
steadytext/providers/base.py
steadytext/providers/cerebras.py
steadytext/providers/jina.py
steadytext/providers/openai.py
steadytext/providers/openrouter.py
steadytext/providers/openrouter.pyi
steadytext/providers/openrouter_config.py
steadytext/providers/openrouter_errors.py
steadytext-2025.10.31.dist-info/METADATA
steadytext-2025.10.31.dist-info/WHEEL
steadytext-2025.10.31.dist-info/entry_points.txt
steadytext-2025.10.31.dist-info/licenses/LICENSE
steadytext-2025.10.31.dist-info/licenses/LICENSE-GEMMA.txt
steadytext-2025.10.31.dist-info/RECORD
