Metadata-Version: 2.4
Name: steadytext
Version: 2025.10.31
Summary: Deterministic text generation and embedding with zero configuration
Project-URL: Homepage, https://github.com/julep-ai/steadytext
Project-URL: Bug Tracker, https://github.com/julep-ai/steadytext/issues
Author-email: SteadyText Community <singh@diwank.name>
License: MIT License
License-File: LICENSE
License-File: LICENSE-GEMMA.txt
Classifier: Development Status :: 3 - Alpha
Classifier: Intended Audience :: Developers
Classifier: License :: OSI Approved :: MIT License
Classifier: Programming Language :: Python :: 3.10
Classifier: Programming Language :: Python :: 3.11
Classifier: Programming Language :: Python :: 3.12
Classifier: Programming Language :: Python :: 3.13
Classifier: Topic :: Scientific/Engineering :: Artificial Intelligence
Classifier: Topic :: Software Development :: Libraries :: Python Modules
Classifier: Typing :: Typed
Requires-Python: <3.14,>=3.10
Requires-Dist: chonkie>=0.2.1
Requires-Dist: click>=8.0.0
Requires-Dist: faiss-cpu>=1.7.0
Requires-Dist: httpx>=0.27.2
Requires-Dist: huggingface-hub>=0.32.0
Requires-Dist: llama-cpp-python>=0.3.16
Requires-Dist: numpy>=1.21.0
Requires-Dist: openai>=1.102.0
Requires-Dist: pydantic>=2.11.7
Requires-Dist: pyzmq>=22.0.0
Requires-Dist: requests>=2.32.5
Requires-Dist: tomli-w>=1.2.0
Requires-Dist: tomli>=2.2.0
Requires-Dist: tqdm>=4
Requires-Dist: voyageai>=0.3.4
Provides-Extra: benchmark
Requires-Dist: matplotlib; extra == 'benchmark'
Requires-Dist: pandas; extra == 'benchmark'
Requires-Dist: psutil; extra == 'benchmark'
Requires-Dist: tabulate; extra == 'benchmark'
Provides-Extra: test
Requires-Dist: pytest; extra == 'test'
Requires-Dist: pytest-cov; extra == 'test'
Requires-Dist: pytest-xdist; extra == 'test'
